vysion/__init__.py
vysion/client/__init__.py
vysion/client/client.py
vysion/client/error.py
vysion/dto/__init__.py
vysion/dto/dto.py
vysion/dto/tag.py
vysion/dto/util.py
vysion/model/__init__.py
vysion/model/enum/__init__.py
vysion/model/enum/languages.py
vysion/model/enum/networks.py
vysion/model/enum/ransom_groups.py
vysion/model/enum/services.py
vysion/taxonomy/__init__.py
vysion/taxonomy/flavours.py
vysion/taxonomy/taxonomy.py
vysion/version.py
vysion-2.2.0.dist-info/LICENSE
vysion-2.2.0.dist-info/METADATA
vysion-2.2.0.dist-info/WHEEL
vysion-2.2.0.dist-info/RECORD
