Metadata-Version: 2.1
Name: vysion
Version: 2.2.0
Summary: The official Python client library for Vysion
Home-page: https://vysion.ai
License: Apache-2.0
Author: Javier Junquera-Sánchez
Author-email: javier.junquera@byronlabs.io
Requires-Python: >=3.8.0,<4.0.0
Classifier: License :: OSI Approved :: Apache Software License
Classifier: Operating System :: OS Independent
Classifier: Programming Language :: Python :: 3
Classifier: Programming Language :: Python :: 3.8
Classifier: Programming Language :: Python :: 3.9
Classifier: Programming Language :: Python :: 3.10
Classifier: Programming Language :: Python :: 3.11
Classifier: Programming Language :: Python :: 3.12
Requires-Dist: pydantic (>=2.0.1,<3.0.0)
Requires-Dist: pymisp (>=2.4.194,<3.0.0)
Requires-Dist: requests (>=2.28.1,<3.0.0)
Requires-Dist: softenum (==1.0.1)
Project-URL: Documentation, https://developers.vysion.ai
Project-URL: Repository, https://github.com/ByronLabs/vysion-py
